README.md
license.txt
setup.py
test/test_tfidf_transformer.py
tfidf_transformation_berk/__init__.py
tfidf_transformation_berk/tfidf.py
tfidf_transformation_berk/tfidf_transformation_berk.py
tfidf_transformation_berk.egg-info/PKG-INFO
tfidf_transformation_berk.egg-info/SOURCES.txt
tfidf_transformation_berk.egg-info/dependency_links.txt
tfidf_transformation_berk.egg-info/top_level.txt